consult/__init__.py
consult/__main__.py
consult/inputs.yaml
consult-0.2.1.dist-info/entry_points.txt
consult-0.2.1.dist-info/LICENSE
consult-0.2.1.dist-info/WHEEL
consult-0.2.1.dist-info/METADATA
consult-0.2.1.dist-info/RECORD
