Metadata-Version: 2.1
Name: consult
Version: 0.2.1
Summary: Receive a quick consultation from Engineering!
Home-page: https://github.com/vaneseltine/consult
License: AGPL-3.0-or-later
Keywords: humor
Author: Matt VanEseltine
Author-email: vaneseltine@gmail.com
Requires-Python: >=3.9,<4.0
Classifier: License :: OSI Approved :: GNU Affero General Public License v3 or later (AGPLv3+)
Classifier: Programming Language :: Python :: 3
Classifier: Programming Language :: Python :: 3.9
Requires-Dist: click (>=7.1,<8.0)
Requires-Dist: pyyaml (==5.4.1)
Project-URL: Repository, https://github.com/vaneseltine/consult
